AUTHORS
COPYING
MANIFEST.in
README.creole
setup.py
src/md.egg-info/PKG-INFO
src/md.egg-info/SOURCES.txt
src/md.egg-info/dependency_links.txt
src/md.egg-info/entry_points.txt
src/md.egg-info/requires.txt
src/md.egg-info/top_level.txt
src/mdlib/__init__.py
src/mdlib/api.py
src/mdlib/cli.py
src/mdlib/cmdln.py
src/mdlib/filterprocessor.py
src/mdlib/hdrparser.py
src/mdlib/pull.py
src/mdlib/tests.py