Metadata-Version: 1.0
Name: md
Version: 0.81
Summary: Maildir command line mail client and library
Home-page: http://github.com/nicferrier/md
Author: Nic Ferrier
Author-email: nic@ferrier.me.uk
License: GNU GPL v3
Download-URL: http://github.com/nicferrier/md/downloads
Platform: unix
Classifier: Development Status :: 3 - Alpha
Classifier: Intended Audience :: Developers
Classifier: License :: OSI Approved :: GNU General Public License (GPL)
Classifier: Operating System :: OS Independent
Classifier: Programming Language :: Python
Classifier: Topic :: Utilities
Classifier: Topic :: Communications :: Email
